MagicTools/Atom.py
MagicTools/AtomType.py
MagicTools/Bond.py
MagicTools/BondType.py
MagicTools/DF.py
MagicTools/DFs_Accumulator_Process.py
MagicTools/DFset.py
MagicTools/MTException.py
MagicTools/MagicTools.py
MagicTools/MolType.py
MagicTools/Molecule.py
MagicTools/System.py
MagicTools/Trajectory.py
MagicTools/__init__.py
MagicTools/object_magictools.py
MagicTools/rdf.py
magic_3_tools-0.1.1.dist-info/licenses/LICENSE
magic_3_tools-0.1.1.dist-info/METADATA
magic_3_tools-0.1.1.dist-info/WHEEL
magic_3_tools-0.1.1.dist-info/entry_points.txt
magic_3_tools-0.1.1.dist-info/top_level.txt
magic_3_tools-0.1.1.dist-info/RECORD
