Metadata-Version: 2.4
Name: magic-3-tools
Version: 0.1.1
Summary: A library for molecular dynamics analysis and RDF calculations
Author-email: Alexander Lyubartsev <alexander.lyubartsev@su.se>
License: GPL-3.0
Project-URL: Homepage, https://bitbucket.org/magic-su/magic-3/src/master/
Project-URL: Repository, https://github.com/mposysoev/MagicTools
Project-URL: Issues, https://github.com/mposysoev/MagicTools/issues
Keywords: molecular dynamics,RDF,radial distribution function,chemistry,physics
Classifier: Development Status :: 3 - Alpha
Classifier: Intended Audience :: Science/Research
Classifier: License :: OSI Approved :: GNU General Public License v3 (GPLv3)
Classifier: Programming Language :: Python :: 3
Classifier: Programming Language :: Python :: 3.10
Classifier: Programming Language :: Python :: 3.11
Classifier: Programming Language :: Python :: 3.12
Classifier: Topic :: Scientific/Engineering :: Chemistry
Classifier: Topic :: Scientific/Engineering :: Physics
Requires-Python: >=3.10
License-File: LICENSE
Requires-Dist: numpy>=1.20.0
Requires-Dist: pandas>=1.3.0
Requires-Dist: matplotlib>=3.3.0
Provides-Extra: dev
Requires-Dist: pytest>=7.0; extra == "dev"
Requires-Dist: black; extra == "dev"
Requires-Dist: flake8; extra == "dev"
Provides-Extra: trajectory
Requires-Dist: mdtraj>=1.9.0; extra == "trajectory"
Dynamic: license-file
